MANIFEST.in
Makefile
README
setup.cfg
setup.py
test/__init__.py
test/__init__.pyc
test/test_basics.py
test/test_compile.py
test/test_tiddler.py
test/__pycache__/test_basics.cpython-27-PYTEST.pyc
test/__pycache__/test_compile.cpython-27-PYTEST.pyc
test/__pycache__/test_tiddler.cpython-27-PYTEST.pyc
tiddlywebplugins/__init__.py
tiddlywebplugins.links.egg-info/PKG-INFO
tiddlywebplugins.links.egg-info/SOURCES.txt
tiddlywebplugins.links.egg-info/dependency_links.txt
tiddlywebplugins.links.egg-info/namespace_packages.txt
tiddlywebplugins.links.egg-info/not-zip-safe
tiddlywebplugins.links.egg-info/requires.txt
tiddlywebplugins.links.egg-info/top_level.txt
tiddlywebplugins/links/__init__.py
tiddlywebplugins/links/linksmanager.py
tiddlywebplugins/links/parser.py