Metadata-Version: 1.0
Name: tiddlywebplugins.links
Version: 1.1.2
Summary: Maintain a tiddlers links database
Home-page: http://pypi.python.org/pypi/tiddlywebplugins.links
Author: Chris Dent
Author-email: cdent@peermore.com
License: UNKNOWN
Platform: Posix; MacOS X; Windows
